ctlib_geoip/__init__.py
ctlib_geoip/async_client.py
ctlib_geoip/base.py
ctlib_geoip/cache.py
ctlib_geoip/client.py
ctlib_geoip/constants.py
ctlib_geoip/exceptions.py
ctlib_geoip/geo_tree.py
ctlib_geoip/models.py
ctlib_geoip/types.py
ctlib_geoip/data/GEO_CN.jsonl
ctlib_geoip/data/GEO_HK.jsonl
ctlib_geoip/data/GEO_MO.jsonl
ctlib_geoip/data/GEO_TW.jsonl
ctlib_geoip-0.1.1.dist-info/METADATA
ctlib_geoip-0.1.1.dist-info/WHEEL
ctlib_geoip-0.1.1.dist-info/RECORD
