Metadata-Version: 2.4
Name: ctlib-geoip
Version: 0.1.1
Summary: A GeoIP SDK supporting both sync and async operations
Author-email: jimin <jimin@codetech.top>
License: MIT
Keywords: codetech,ctlib
Classifier: Development Status :: 4 - Beta
Classifier: Intended Audience :: Developers
Classifier: License :: OSI Approved :: MIT License
Classifier: Operating System :: OS Independent
Classifier: Programming Language :: Python :: 3
Classifier: Programming Language :: Python :: 3.8
Classifier: Programming Language :: Python :: 3.9
Classifier: Programming Language :: Python :: 3.10
Classifier: Programming Language :: Python :: 3.11
Classifier: Programming Language :: Python :: 3.12
Requires-Python: >=3.8
Requires-Dist: cachetools>=5.0.0
Requires-Dist: httpx>=0.24.0
Requires-Dist: pydantic>=2.0.0
